{
    "@module": "dpdata.system",
    "@class": "LabeledSystem",
    "data": {
        "atom_numbs": [
            2
        ],
        "atom_names": [
            "Mo"
        ],
        "atom_types": {
            "@module": "numpy",
            "@class": "array",
            "dtype": "int64",
            "data": [
                0,
                0
            ]
        },
        "orig": {
            "@module": "numpy",
            "@class": "array",
            "dtype": "int64",
            "data": [
                0,
                0,
                0
            ]
        },
        "cells": {
            "@module": "numpy",
            "@class": "array",
            "dtype": "float64",
            "data": [
                [
                    [
                        2.8069548261,
                        0.0,
                        0.0
                    ],
                    [
                        0.0,
                        2.8069548261,
                        0.0
                    ],
                    [
                        0.0,
                        0.0,
                        2.8069548261
                    ]
                ],
                [
                    [
                        2.8069548261,
                        0.0,
                        0.0
                    ],
                    [
                        0.0,
                        2.8069548261,
                        0.0
                    ],
                    [
                        0.0,
                        0.0,
                        2.8069548261
                    ]
                ]
            ]
        },
        "coords": {
            "@module": "numpy",
            "@class": "array",
            "dtype": "float64",
            "data": [
                [
                    [
                        0.0,
                        0.0,
                        0.0
                    ],
                    [
                        1.40347741305,
                        1.40347741305,
                        1.40347741305
                    ]
                ],
                [
                    [
                        -0.09016893266074075,
                        -0.09016893266074075,
                        -0.09016893266074075
                    ],
                    [
                        1.4936452229288104,
                        1.4936452229288104,
                        1.4936452229288104
                    ]
                ]
            ]
        },
        "energies": {
            "@module": "numpy",
            "@class": "array",
            "dtype": "float64",
            "data": [
                -15.641832,
                -16.05492
            ]
        },
        "forces": {
            "@module": "numpy",
            "@class": "array",
            "dtype": "float64",
            "data": [
                [
                    [
                        -9.00958e-10,
                        -9.00959e-10,
                        -9.00957e-10
                    ],
                    [
                        9.00958e-10,
                        9.00959e-10,
                        9.00957e-10
                    ]
                ],
                [
                    [
                        -1.00391e-11,
                        -1.00003e-11,
                        -9.92439e-12
                    ],
                    [
                        1.00391e-11,
                        9.99961e-12,
                        9.92395e-12
                    ]
                ]
            ]
        },
        "virials": {
            "@module": "numpy",
            "@class": "array",
            "dtype": "float64",
            "data": [
                [
                    [
                        69.6424296262675,
                        8.881783501571631e-16,
                        1.0252215031955963e-15
                    ],
                    [
                        8.881783501571631e-16,
                        69.6424296262675,
                        3.2751576696554664e-15
                    ],
                    [
                        1.0252215031955963e-15,
                        3.2751576696554664e-15,
                        69.6424296262675
                    ]
                ],
                [
                    [
                        27.715846015072966,
                        -1.663676753317034,
                        -1.663676753317034
                    ],
                    [
                        -1.663676753317034,
                        27.715846015072966,
                        -1.663676753317034
                    ],
                    [
                        -1.663676753317034,
                        -1.663676753317034,
                        27.715846015072966
                    ]
                ]
            ]
        },
        "stress": {
            "@module": "numpy",
            "@class": "array",
            "dtype": "float64",
            "data": [
                [
                    [
                        5045.195900000001,
                        6.4343444e-14,
                        7.4271437e-14
                    ],
                    [
                        6.4343444e-14,
                        5045.195900000001,
                        2.3726645000000003e-13
                    ],
                    [
                        7.4271437e-14,
                        2.3726645000000003e-13,
                        5045.195900000001
                    ]
                ],
                [
                    [
                        2007.8546000000001,
                        -120.52387,
                        -120.52387
                    ],
                    [
                        -120.52387,
                        2007.8546000000001,
                        -120.52387
                    ],
                    [
                        -120.52387,
                        -120.52387,
                        2007.8546000000001
                    ]
                ]
            ]
        }
    }
}